t/__init__.py
t/thomas.py
t5omass-1.3.dist-info/LICENSE.txt
t5omass-1.3.dist-info/METADATA
t5omass-1.3.dist-info/WHEEL
t5omass-1.3.dist-info/top_level.txt
t5omass-1.3.dist-info/RECORD
