Metadata-Version: 2.1
Name: t5omass
Version: 1.3
Summary: This is a library to check email (Hotmail, Gmail) if is availabe, get instagram information by usernam, get reset of user instagram, check if email registered in instagram, And many more features that may be added soon.
Home-page: https://t.me/t5omas
Author: t5omas
Author-email: t5omas@mail.com
Classifier: Programming Language :: Python :: 3
Classifier: License :: OSI Approved :: MIT License
Classifier: Operating System :: OS Independent
Requires-Python: >=3.6
License-File: LICENSE.txt
Requires-Dist: requests
Requires-Dist: uuid
Requires-Dist: user-agent
